Metadata-Version: 1.1
Name: aylien-apiclient
Version: 0.3.0
Summary: AYLIEN Text API Client Library for Python
Home-page: https://github.com/AYLIEN/aylien_textapi_python
Author: Aylien, Inc.
Author-email: UNKNOWN
License: Apache 2.0
Keywords: aylien text api client
Platform: UNKNOWN
Classifier: Development Status :: 3 - Alpha
Classifier: Intended Audience :: Developers
Classifier: License :: OSI Approved :: Apache Software License
Classifier: Operating System :: POSIX
Classifier: Topic :: Internet :: WWW/HTTP
